MANIFEST.in
README.rst
config
configcnc
configpync
configpync_s3
configtest
setup.py
userbased_nc_bench
userbased_nc_bench/Makefile
userbased_nc_bench/__init__.py
userbased_nc_bench/netcdf_creation.py
userbased_nc_bench/readfile_bin.c
userbased_nc_bench/readfile_bin.py
userbased_nc_bench/readfile_nc.c
userbased_nc_bench/readfile_nc.py
userbased_nc_bench/readfile_s3.py
userbased_nc_bench/userbased_nc_bench.py
userbased_nc_bench.egg-info/PKG-INFO
userbased_nc_bench.egg-info/SOURCES.txt
userbased_nc_bench.egg-info/dependency_links.txt
userbased_nc_bench.egg-info/not-zip-safe
userbased_nc_bench.egg-info/requires.txt
userbased_nc_bench.egg-info/top_level.txt